setup.cfg
setup.py
schemaTest/__init__.py
schemaTest/schema_test.py
schemaTest.egg-info/PKG-INFO
schemaTest.egg-info/SOURCES.txt
schemaTest.egg-info/dependency_links.txt
schemaTest.egg-info/requires.txt
schemaTest.egg-info/top_level.txt
schemaTest/schema_files/actor_imdb.json
schemaTest/schema_files/album.json
schemaTest/schema_files/album_kaola.json
schemaTest/schema_files/album_kuwo.json
schemaTest/schema_files/article.json
schemaTest/schema_files/artist.json
schemaTest/schema_files/artist_kuwo.json
schemaTest/schema_files/artist_qq_new.json
schemaTest/schema_files/blog.json
schemaTest/schema_files/book.json
schemaTest/schema_files/book_ireader.json
schemaTest/schema_files/book_qq.json
schemaTest/schema_files/book_shuqi.json
schemaTest/schema_files/deal_groupon.json
schemaTest/schema_files/deal_livingsocial.json
schemaTest/schema_files/dictionary.json
schemaTest/schema_files/encyclopedia.json
schemaTest/schema_files/event.json
schemaTest/schema_files/event_eventbrite.json
schemaTest/schema_files/event_eventful.json
schemaTest/schema_files/event_last.json
schemaTest/schema_files/event_meetup.json
schemaTest/schema_files/event_songkick.json
schemaTest/schema_files/event_stubhub.json
schemaTest/schema_files/event_vividseats.json
schemaTest/schema_files/event_yelp.json
schemaTest/schema_files/hotel.json
schemaTest/schema_files/hotel_airbnb.json
schemaTest/schema_files/hotel_booking.json
schemaTest/schema_files/hotel_expedia.json
schemaTest/schema_files/hotel_goibibo.json
schemaTest/schema_files/hotel_makemytrip.json
schemaTest/schema_files/hotel_tripadvisor.json
schemaTest/schema_files/local.json
schemaTest/schema_files/localbusiness_foursquare.json
schemaTest/schema_files/movie.json
schemaTest/schema_files/movie_bookmyshow.json
schemaTest/schema_files/movie_fandango.json
schemaTest/schema_files/movie_hulu.json
schemaTest/schema_files/movie_imdb.json
schemaTest/schema_files/movie_iqiyi.json
schemaTest/schema_files/movie_mtime.json
schemaTest/schema_files/movie_tudou.json
schemaTest/schema_files/movietheater_fandango.json
schemaTest/schema_files/musicalbum_last.json
schemaTest/schema_files/musicalbum_saavn.json
