Metadata-Version: 1.0
Name: schemaTest
Version: 0.5
Summary: schema test for quixey
Home-page: UNKNOWN
Author: dyf
Author-email: 1821367759@qq.com
License: UNKNOWN
Platform: UNKNOWN
